{"cameraMode":{"drawMode":0,"name":"Shaded","section":"Shading Mode"},"sceneLighting":true,"audioPlay":false,"sceneViewState":{"m_AlwaysRefresh":false,"showFog":true,"showSkybox":true,"showFlares":true,"showImageEffects":true,"showParticleSystems":true,"showVisualEffectGraphs":true,"m_FxEnabled":true},"in2DMode":false,"pivot":{"x":3.237997055053711,"y":169.98497009277345,"z":70.13468170166016},"rotation":{"x":-0.11400150507688523,"y":-0.3592931032180786,"z":0.04458698630332947,"w":-0.9252826571464539},"size":280.49639892578127,"orthographic":false}